sqlgap/__init__.py
sqlgap/dbapi.py
sqlgap-0.1.1.dist-info/DESCRIPTION.rst
sqlgap-0.1.1.dist-info/METADATA
sqlgap-0.1.1.dist-info/RECORD
sqlgap-0.1.1.dist-info/WHEEL
sqlgap-0.1.1.dist-info/metadata.json
sqlgap-0.1.1.dist-info/top_level.txt
