Metadata-Version: 2.0
Name: sqlgap
Version: 0.1.1
Summary: A very simple interface into a SQL server
Home-page: https://github.com/FoleyDiver/sqlgap
Author: Steve Foley
Author-email: sfoley1988@gmail.com
License: GPLv2+
Download-URL: https://github.com/FoleyDiver/sqlgap/archive/v0.1.1.tar.gz
Platform: UNKNOWN
Classifier: Development Status :: 3 - Alpha
Classifier: License :: OSI Approved :: GNU General Public License v2 or later (GPLv2+)
Classifier: Intended Audience :: Developers
Classifier: Programming Language :: Python :: 3.4
Classifier: Programming Language :: Python :: 3.5
Classifier: Programming Language :: Python :: 3.6
